desktop_file/Arg.py
desktop_file/Args.py
desktop_file/LinuxShortcut.py
desktop_file/WindowsShortcut.py
desktop_file/__init__.py
desktop_file/__main__.py
desktop_file/help.txt
desktop_file-1.2.data/scripts/desktop-file
desktop_file-1.2.dist-info/LICENSE.md
desktop_file-1.2.dist-info/METADATA
desktop_file-1.2.dist-info/WHEEL
desktop_file-1.2.dist-info/top_level.txt
desktop_file-1.2.dist-info/RECORD
