Metadata-Version: 2.1
Name: desktop-file
Version: 1.2
Summary: desktop-file is a tool to create desktop shortcuts for windows and linux.
Home-page: https://github.com/PyRectangle/DesktopFile
Author: PyRectangle
Author-email: PyRectangle@web.de
License: MIT
Platform: UNKNOWN
Requires-Dist: pypiwin32 ; platform_system == "Windows"
